nvidia/__init__.pyi
nvidia/nvcomp/__init__.pyi
nvidia/nvcomp/nvcomp_impl.pyi
nvidia/nvimgcodec/__init__.pyi
nvidia/nvimgcodec/nvimgcodec_impl.pyi
nvidia/nvjpeg/__init__.pyi
nvidia/nvjpeg2k/__init__.pyi
nvidia/nvtiff/__init__.pyi
nvidia-nvimgcodec-cu11-stubs/__init__.py
nvidia-nvimgcodec-cu11-stubs/py.typed
nvidia_nvimgcodec_cu11_stubs-0.5.0.13.7.dist-info/METADATA
nvidia_nvimgcodec_cu11_stubs-0.5.0.13.7.dist-info/WHEEL
nvidia_nvimgcodec_cu11_stubs-0.5.0.13.7.dist-info/licenses/LICENSE
nvidia_nvimgcodec_cu11_stubs-0.5.0.13.7.dist-info/RECORD
