Metadata-Version: 2.4
Name: nvidia-nvimgcodec-cu11-stubs
Version: 0.5.0.13.7
Summary: Type stubs for NVIDIA NVIMGCODEC CUDA 12 bindings
Project-URL: Homepage, https://github.com/sync-dev-org/nvidia-nvimgcodec-stubs
Author-email: minamik <mia@sync.dev>
License: MIT License
License-File: LICENSE
Classifier: Development Status :: 4 - Beta
Classifier: Intended Audience :: Developers
Classifier: License :: OSI Approved :: MIT License
Classifier: Programming Language :: Python :: 3
Classifier: Programming Language :: Python :: 3.10
Classifier: Programming Language :: Python :: 3.11
Classifier: Programming Language :: Python :: 3.12
Classifier: Programming Language :: Python :: 3.13
Classifier: Typing :: Stubs Only
Requires-Python: >=3.10
Requires-Dist: nvidia-nvimgcodec-cu11[all]>=0.5.0.13
Provides-Extra: dev
Requires-Dist: black>=23.7.0; extra == 'dev'
Requires-Dist: flake8>=6.1.0; extra == 'dev'
Requires-Dist: pybind11-stubgen>=2.5.4; extra == 'dev'
Requires-Dist: pytest>=8.3.5; extra == 'dev'
Requires-Dist: twine>=6.1.0; extra == 'dev'
